{
  "pattern_recognition": "Linked List Manipulation, as this problem requires understanding of pointers and node relationships. Signals include reversing the order of nodes.",
  "approaches": [
    {
      "title": "Brute Force",
      "intuition": "Create a new linked list and insert nodes in reverse order.",
      "algorithm": "1. Initialize a new linked list. 2. Traverse the original list and insert each node at the head of the new list.",
      "complexity": "See approach.",
      "code": "def reverseLinkedList(data):\n    values = data.split()\n    new_head = None\n    for value in values:\n        new_node = value\n        new_head = new_node + ' ' + new_head if new_head else new_node\n    return new_head.strip()",
      "code_python": "def reverseLinkedList(data):\n    values = data.split()\n    new_head = None\n    for value in values:\n        new_node = value\n        new_head = new_node + ' ' + new_head if new_head else new_node\n    return new_head.strip()",
      "code_javascript": "function reverseLinkedList(data) {\n    let newList = [];\n    for (let i = data.length - 1; i >= 0; i--) {\n        newList.push(data[i]);\n    }\n    return newList;\n}",
      "code_java": "class ListNode {\n    int val;\n    ListNode next;\n    ListNode(int x) {\n        val = x;\n    }\n}\nclass Solution {\n    public ListNode reverseLinkedList(ListNode data) {\n        ListNode newHead = null;\n        while (data != null) {\n            ListNode newNode = new ListNode(data.val);\n            newNode.next = newHead;\n            newHead = newNode;\n            data = data.next;\n        }\n        return newHead;\n    }\n}",
      "code_cpp": "#include <vector>\n#include <string>\nusing namespace std;\nstruct ListNode {\n    int val;\n    ListNode *next;\n    ListNode(int x) : val(x), next(nullptr) {\n    }\n}\n;\nclass Solution {\n    public:\n    ListNode* reverseLinkedList(ListNode* head) {\n        ListNode* newHead = nullptr;\n        while (head != nullptr) {\n            ListNode* newNode = new ListNode(head->val);\n            newNode->next = newHead;\n            newHead = newNode;\n            head = head->next;\n        }\n        return newHead;\n    }\n}\n;",
      "code_go": "package main\n\ntype ListNode struct {\n    Val  int\n    Next *ListNode\n}\n\nfunc reverseLinkedList(data *ListNode) *ListNode {\n    newHead := &ListNode{}\n    for data != nil {\n        newNode := &ListNode{Val: data.Val}\n        newNode.Next = newHead.Next\n        newHead.Next = newNode\n        data = data.Next\n    }\n    return newHead.Next\n}",
      "code_csharp": "public class ListNode {\n    public int val;\n    public ListNode next;\n    public ListNode(int x) { val = x; }\n}\n\npublic class Solution {\n    public ListNode reverseLinkedList(ListNode data) {\n        ListNode newHead = null;\n        while (data != null) {\n            ListNode newNode = new ListNode(data.val);\n            newNode.next = newHead;\n            newHead = newNode;\n            data = data.next;\n        }\n        return newHead;\n    }\n}"
    },
    {
      "title": "Optimal Approach",
      "intuition": "Reverse the pointers in the existing linked list without using extra space.",
      "algorithm": "1. Initialize three pointers: previous, current, and next. 2. Iterate through the list, adjusting pointers to reverse the links.",
      "complexity": "See approach.",
      "code": "def reverseLinkedList(data):\n    values = data.split()\n    new_head = None\n    for value in values:\n        new_node = value\n        new_head = new_node + ' ' + new_head if new_head else new_node\n    return new_head.strip()",
      "code_python": "def reverseLinkedList(data):\n    values = data.split()\n    new_head = None\n    for value in values:\n        new_node = value\n        new_head = new_node + ' ' + new_head if new_head else new_node\n    return new_head.strip()",
      "code_javascript": "function reverseLinkedList(data) {\n    let previous = null;\n    let current = data;\n    let next = null;\n    while (current !== null) {\n        next = current.next; // store next node\n        current.next = previous; // reverse current node's pointer\n        previous = current; // move previous to current\n        current = next; // move to next node\n    }\n    return previous; // new head of the reversed list\n}",
      "code_java": "class ListNode {\n    int val;\n    ListNode next;\n    ListNode(int x) {\n        val = x;\n    }\n}\nclass Solution {\n    public ListNode reverseLinkedList(ListNode data) {\n        ListNode previous = null;\n        ListNode current = data;\n        ListNode next = null;\n        while (current != null) {\n            next = current.next; // Store next node\n            current.next = previous; // Reverse the link\n            previous = current; // Move previous to current\n            current = next; // Move to next node\n        }\n        return previous; // New head of the reversed list\n    }\n}",
      "code_cpp": "#include <vector>\n#include <string>\nusing namespace std;\nstruct ListNode {\n    int val;\n    ListNode *next;\n    ListNode(int x) : val(x), next(nullptr) {\n    }\n}\n;\nclass Solution {\n    public:\n    ListNode* reverseLinkedList(ListNode* head) {\n        ListNode* previous = nullptr;\n        ListNode* current = head;\n        ListNode* next = nullptr;\n        while (current != nullptr) {\n            next = current->next; // Store next node\n            current->next = previous; // Reverse current node's pointer\n            previous = current; // Move previous to current\n            current = next; // Move to next node\n        }\n        return previous; // New head of the reversed list\n    }\n}\n;",
      "code_go": "package main\n\ntype ListNode struct {\n    Val  int\n    Next *ListNode\n}\n\nfunc reverseLinkedList(data *ListNode) *ListNode {\n    var previous *ListNode\n    current := data\n    var next *ListNode\n\n    for current != nil {\n        next = current.Next\n        current.Next = previous\n        previous = current\n        current = next\n    }\n\n    return previous\n}",
      "code_csharp": "public class ListNode {\n    public int val;\n    public ListNode next;\n    public ListNode(int x) { val = x; }\n}\n\npublic class Solution {\n    public ListNode reverseLinkedList(ListNode data) {\n        ListNode previous = null;\n        ListNode current = data;\n        ListNode next = null;\n\n        while (current != null) {\n            next = current.next; // Store next node\n            current.next = previous; // Reverse the link\n            previous = current; // Move previous to current\n            current = next; // Move to next node\n        }\n        return previous; // New head of the reversed list\n    }\n}"
    }
  ],
  "dry_run": "Input: 1 2 3 4 5. Start with head pointing to 1. Initialize previous as null. Current points to head. While current is not null, set next to current.next, current.next to previous, then move previous to current and current to next. Repeat until current is null. The new head will be previous, which points to 5.",
  "edge_cases": "Empty input results in null. A single element list remains unchanged. Duplicates are handled as normal nodes. Large inputs should be tested for performance. Overflow is not a concern since we are only reversing pointers.",
  "common_pitfalls": "1. Forgetting to update the next pointer can lead to losing access to the rest of the list. 2. Not handling the case of an empty list can cause null pointer exceptions. 3. Incorrectly setting the new head can result in returning the wrong list.",
  "youtube_video_id": null
}